README.rst
pyproject.toml
rbext/__init__.py
rbext/_version.py
rbext.egg-info/PKG-INFO
rbext.egg-info/SOURCES.txt
rbext.egg-info/dependency_links.txt
rbext.egg-info/top_level.txt