Metadata-Version: 2.1
Name: rbext
Version: 0.1
Summary: Review Board extension-building tools and build backend
Author-email: "Beanbag, Inc." <support@beanbaginc.com>
Maintainer-email: "Beanbag, Inc." <support@beanbaginc.com>
Project-URL: homepage, https://www.reviewboard.org
Requires-Python: >=3.8
